rbfoptgo/__init__.py
rbfoptgo/client.py
rbfoptgo/common.py
rbfoptgo/config.py
rbfoptgo/evaluator.py
rbfoptgo/main.py
rbfoptgo/names.py
rbfoptgo/plot.py
rbfoptgo/plot_debug.py
rbfoptgo/report.py
rbfoptgo/test_plot.py
rbfopt_go-0.5.4.dist-info/LICENSE
rbfopt_go-0.5.4.dist-info/METADATA
rbfopt_go-0.5.4.dist-info/WHEEL
rbfopt_go-0.5.4.dist-info/entry_points.txt
rbfopt_go-0.5.4.dist-info/top_level.txt
rbfopt_go-0.5.4.dist-info/RECORD
