Metadata-Version: 2.1
Name: rbfopt-go
Version: 0.5.4
Summary: Find better configuration of your Go service with derivative-free optimization algorithms
Home-page: https://github.com/newcloudtechnologies/rbfopt-go
Author: Vitaly Isaev
Author-email: vitalyisaev2@gmail.com
License: UNKNOWN
Platform: UNKNOWN
Classifier: Programming Language :: Python :: 3
Classifier: License :: OSI Approved :: MIT License
Classifier: Operating System :: OS Independent
Classifier: Topic :: Scientific/Engineering :: Mathematics
Requires-Python: >=3.7
License-File: LICENSE
Requires-Dist: Pyomo (==6.1.2)
Requires-Dist: adjustText
Requires-Dist: colorhash (==1.0.4)
Requires-Dist: jsons
Requires-Dist: matplotlib
Requires-Dist: numpy
Requires-Dist: pandas
Requires-Dist: rbfopt (==4.2.2)
Requires-Dist: requests
Requires-Dist: scipy
Requires-Dist: urllib3
